[
    {
        "cliente_id": 10,
        "estado_reserva": 1,
        "fecha_devolucion": "2024-07-06",
        "fecha_prestamo": "2024-06-30",
        "libro_id": 5,
        "reserva_id": 1
    },
    {
        "cliente_id": 3,
        "estado_reserva": 2,
        "fecha_devolucion": "2024-07-18",
        "fecha_prestamo": "2024-06-30",
        "libro_id": 3,
        "reserva_id": 2
    },
    {
        "cliente_id": 3,
        "estado_reserva": 1,
        "fecha_devolucion": "2024-08-01",
        "fecha_prestamo": "2024-06-30",
        "libro_id": 7,
        "reserva_id": 3
    },
    {
        "cliente_id": 3,
        "estado_reserva": 1,
        "fecha_devolucion": "2024-07-10",
        "fecha_prestamo": "2024-06-30",
        "libro_id": 12,
        "reserva_id": 4
    }
]